__init__.py
rev_ai/__init__.py
rev_ai/apiclient.py
rev_ai/baseclient.py
rev_ai/custom_vocabularies_client.py
rev_ai/generic_api_client.py
rev_ai/language_identification_client.py
rev_ai/sentiment_analysis_client.py
rev_ai/streamingclient.py
rev_ai/topic_extraction_client.py
rev_ai/utils.py
rev_ai/models/__init__.py
rev_ai/models/customer_url_data.py
rev_ai/models/customvocabulary.py
rev_ai/models/revaiapi_deployment_config_constants.py
rev_ai/models/asynchronous/__init__.py
rev_ai/models/asynchronous/account.py
rev_ai/models/asynchronous/caption_type.py
rev_ai/models/asynchronous/group_channels_type.py
rev_ai/models/asynchronous/job.py
rev_ai/models/asynchronous/job_status.py
rev_ai/models/asynchronous/speaker_name.py
rev_ai/models/asynchronous/summarization_formatting_options.py
rev_ai/models/asynchronous/summarization_job_status.py
rev_ai/models/asynchronous/summarization_model.py
rev_ai/models/asynchronous/summarization_options.py
rev_ai/models/asynchronous/summary.py
rev_ai/models/asynchronous/transcript.py
rev_ai/models/asynchronous/translation_job_status.py
rev_ai/models/asynchronous/translation_language_options.py
rev_ai/models/asynchronous/translation_model.py
rev_ai/models/asynchronous/translation_options.py
rev_ai/models/insights/__init__.py
rev_ai/models/insights/sentiment_analysis/__init__.py
rev_ai/models/insights/sentiment_analysis/sentiment_analysis_job.py
rev_ai/models/insights/sentiment_analysis/sentiment_analysis_result.py
rev_ai/models/insights/sentiment_analysis/sentiment_value.py
rev_ai/models/insights/topic_extraction/__init__.py
rev_ai/models/insights/topic_extraction/topic_extraction_job.py
rev_ai/models/insights/topic_extraction/topic_extraction_result.py
rev_ai/models/language_id/__init__.py
rev_ai/models/language_id/language_id_job.py
rev_ai/models/language_id/language_id_result.py
rev_ai/models/streaming/__init__.py
rev_ai/models/streaming/mediaconfig.py
rev_ai-2.21.0.dist-info/LICENSE
rev_ai-2.21.0.dist-info/METADATA
rev_ai-2.21.0.dist-info/WHEEL
rev_ai-2.21.0.dist-info/top_level.txt
rev_ai-2.21.0.dist-info/RECORD
