Metadata-Version: 2.1
Name: rev_ai
Version: 2.21.0
Summary: Rev AI makes speech applications easy to build!
Home-page: https://github.com/revdotcom/revai-python-sdk
Author: Rev Ai
License: MIT license
Keywords: rev_ai
Classifier: License :: OSI Approved :: MIT License
Classifier: Intended Audience :: Developers
Classifier: License :: OSI Approved :: MIT License
Classifier: Natural Language :: English
Classifier: Programming Language :: Python :: 3.8
Classifier: Programming Language :: Python :: 3.9
Classifier: Programming Language :: Python :: 3.10
Classifier: Programming Language :: Python :: 3.11
License-File: LICENSE
Requires-Dist: requests<3.0.0,>=2.21.0
Requires-Dist: six<2.0.0,>=1.12.0
Requires-Dist: websocket-client<1.0.0,>=0.56.0
Requires-Dist: enum34<2.0.0,>=1.1.6; python_version < "3.4"
